LICENSE
MANIFEST.in
README.md
requirements.txt
setup.py
cumulus_process/__init__.py
cumulus_process/cli.py
cumulus_process/handlers.py
cumulus_process/helpers.py
cumulus_process/loggers.py
cumulus_process/process.py
cumulus_process/s3.py
cumulus_process/version.py
cumulus_process.egg-info/PKG-INFO
cumulus_process.egg-info/SOURCES.txt
cumulus_process.egg-info/dependency_links.txt
cumulus_process.egg-info/requires.txt
cumulus_process.egg-info/top_level.txt
example/__init__.py
example/main.py
test/test_cli.py
test/test_example.py
test/test_loggers.py
test/test_process.py
test/test_s3.py