Metadata-Version: 2.1
Name: cumulus_process
Version: 1.5.0
Summary: Library for creating Cumulus Process tasks in Python
Home-page: https://github.com/nasa-cumulus/cumulus-process-py
Author: Matthew Hanson (matthewhanson), Alireza J (scisco)
License: Apache 2.0
Classifier: Programming Language :: Python :: 3.10
License-File: LICENSE
Requires-Dist: boto3~=1.26.90
Requires-Dist: python-json-logger~=0.1
Requires-Dist: dicttoxml~=1.7.4
Requires-Dist: cumulus-message-adapter-python~=2.3.0
